cpca/__init__.py
cpca/exceptions.py
cpca/structures.py
cpca/resources/__init__.py
cpca/resources/pca.csv
cpca_linch-0.4.5.dist-info/licenses/LICENSE
cpca_linch-0.4.5.dist-info/METADATA
cpca_linch-0.4.5.dist-info/WHEEL
cpca_linch-0.4.5.dist-info/top_level.txt
cpca_linch-0.4.5.dist-info/RECORD
