Metadata-Version: 2.4
Name: cpca-linch
Version: 0.4.5
Summary: Chinese Province, City and Area Recognition Utilities (Updated 2025)
Home-page: https://github.com/laofahai/cpca-linch
Author: laofahai
Author-email: 
License: MIT
Keywords: Simplified Chinese,Chinese geographic information,Chinese province city area recognition
Classifier: Intended Audience :: Developers
Classifier: License :: OSI Approved :: MIT License
Classifier: Operating System :: OS Independent
Classifier: Natural Language :: Chinese (Simplified)
Classifier: Programming Language :: Python :: 3.8
Classifier: Programming Language :: Python :: 3.9
Classifier: Programming Language :: Python :: 3.10
Classifier: Programming Language :: Python :: 3.11
Classifier: Programming Language :: Python :: 3.12
Classifier: Topic :: Text Processing
Classifier: Topic :: Text Processing :: Indexing
License-File: LICENSE
Requires-Dist: pandas
Requires-Dist: jieba
Dynamic: author
Dynamic: classifier
Dynamic: description
Dynamic: home-page
Dynamic: keywords
Dynamic: license
Dynamic: license-file
Dynamic: requires-dist
Dynamic: summary
